solutioncatalog
