Metadata-Version: 1.0
Name: solutioncatalog-api
Version: 0.0.5
Summary: Solution Catalog
Home-page: https://pypi.org/project/solutioncatalog-api/
Author: UNKNOWN
Author-email: UNKNOWN
License: UNKNOWN
Keywords: OpenAPI,OpenAPI-Generator,Solution Catalog
Platform: UNKNOWN
